hieuvision/__init__.py
hieuvision/core.py
hieuvision/test/__init__.py
hieuvision/test/test.py
hieuvision/tools/__init__.py
hieuvision/tools/augmenter.py
hieuvision-0.2.0.dist-info/licenses/LICENSE
hieuvision-0.2.0.dist-info/METADATA
hieuvision-0.2.0.dist-info/WHEEL
hieuvision-0.2.0.dist-info/top_level.txt
hieuvision-0.2.0.dist-info/RECORD
