Metadata-Version: 2.4
Name: hieuvision
Version: 0.2.0
Summary: A modular computer vision toolkit with augmentation and more.
Author-email: Hieu Nguyen <nguyenminhhieudn02@gmail.com>
License: MIT
Requires-Python: >=3.6
License-File: LICENSE
Requires-Dist: opencv-python
Requires-Dist: albumentations
Requires-Dist: tqdm
Dynamic: license-file
